image_based_malware_dataloader/SorelSmallDataset.py
image_based_malware_dataloader/__init__.py
image_based_malware_dataloader/advnet_lisacnn.py
image_based_malware_dataloader/malimg.py
image_based_malware_dataloader/malnettiny.py
image_based_malware_dataloader/sorel20m_small.py
image_based_malware_dataloader/zelinka_fractal.py
image_based_malware_dataloader/zelinka_fractal_new.py
image_based_malware_dataloader/zelinka_fractal_old.py
image_based_malware_dataloader-1.4.10.dist-info/METADATA
image_based_malware_dataloader-1.4.10.dist-info/WHEEL
image_based_malware_dataloader-1.4.10.dist-info/top_level.txt
image_based_malware_dataloader-1.4.10.dist-info/RECORD
