Metadata-Version: 2.1
Name: image_based_malware_dataloader
Version: 1.4.10
Summary: Image-based Malware Dataloader
Home-page: https://github.com/Cornelius2121/image-based-malware-dataloader
Author: Cornelius Paardekooper
Author-email: cornelius.paardekooper@uon.edu.au
Keywords: python,dataloader,image-based malware
Classifier: Development Status :: 3 - Alpha
Classifier: Intended Audience :: Science/Research
Classifier: Programming Language :: Python :: 3
Classifier: Operating System :: MacOS :: MacOS X
Classifier: Operating System :: Microsoft :: Windows
Requires-Dist: numpy
Requires-Dist: torch
Requires-Dist: scikit-learn
Requires-Dist: pillow
